search_admin_autocomplete/__init__.py
search_admin_autocomplete/admin.py
search_admin_autocomplete/apps.py
search_admin_autocomplete/models.py
search_admin_autocomplete/tests.py
search_admin_autocomplete/views.py
search_admin_autocomplete/static/easy_autocomplete/easy-autocomplete.css
search_admin_autocomplete/static/easy_autocomplete/easy-autocomplete.min.css
search_admin_autocomplete/static/easy_autocomplete/easy-autocomplete.themes.css
search_admin_autocomplete/static/easy_autocomplete/easy-autocomplete.themes.min.css
search_admin_autocomplete/static/easy_autocomplete/jquery.easy-autocomplete.js
search_admin_autocomplete/static/easy_autocomplete/jquery.easy-autocomplete.min.js
search_admin_autocomplete/static/easy_autocomplete/main.js
search_admin_autocomplete/static/easy_autocomplete/maps/easy-autocomplete.css.map
search_admin_autocomplete/static/easy_autocomplete/maps/easy-autocomplete.min.css.map
search_admin_autocomplete/static/easy_autocomplete/maps/easy-autocomplete.themes.css.map
search_admin_autocomplete/static/easy_autocomplete/maps/easy-autocomplete.themes.min.css.map
search_admin_autocomplete/static/search_admin_autocomplete/css/styles.css
search_admin_autocomplete/templates/search_admin_autocomplete/change_list.html
django_search_admin_autocomplete-0.2.1.dist-info/METADATA
django_search_admin_autocomplete-0.2.1.dist-info/WHEEL
django_search_admin_autocomplete-0.2.1.dist-info/top_level.txt
django_search_admin_autocomplete-0.2.1.dist-info/RECORD
