Metadata-Version: 2.1
Name: django-search-admin-autocomplete
Version: 0.2.1
Summary: Simple django app that add autocomplete to search inside admin panel.
Home-page: https://github.com/linevich/django-search-admin-autocomplete
Author: linevich
Author-email: mail@linevich.net
License: MIT
Platform: UNKNOWN
Classifier: Environment :: Web Environment
Classifier: Framework :: Django
Classifier: Intended Audience :: Developers
Classifier: License :: OSI Approved :: MIT License
Classifier: Operating System :: OS Independent
Classifier: Programming Language :: Python
Classifier: Programming Language :: Python :: 3.5
Classifier: Topic :: Internet :: WWW/HTTP
Classifier: Topic :: Internet :: WWW/HTTP :: Dynamic Content
